README.md
setup.py
areixio/DarJCbFnJjbImjjmWlBUaRzfNJdtQmUC.py
areixio/GwvNMqmIMCiKQbtNrfanSznFByOdviky.py
areixio/VspPqlVzsehUowztmyARKolHcBYwHFnO.py
areixio/__init__.py
areixio/__main__.py
areixio/base.py
areixio/czEVolLfodbbkoBODTMIqxMSQpVwqILK.py
areixio/eAGRYKCyCRLxsZMFYdsQvPugReakIlfl.py
areixio/muuoxqgVYrbAaICzFWtNgPItwVIycFew.py
areixio/rmNSufIvJkXuShZPqvmlSDQNOQlccdHn.py
areixio.egg-info/PKG-INFO
areixio.egg-info/SOURCES.txt
areixio.egg-info/dependency_links.txt
areixio.egg-info/entry_points.txt
areixio.egg-info/not-zip-safe
areixio.egg-info/requires.txt
areixio.egg-info/top_level.txt
areixio/brokers/UDEWZAvVFMabyJwxrzoYjESIJoZPUqig.py
areixio/brokers/__init__.py
areixio/brokers/nwrMoTbHFPAanOkjUeCYBAKBgNJdUKic.py
areixio/databases/PszasNGaEUZTSpZPzYjqKCglcQDZyuaA.py
areixio/databases/RxrCKuYFsnTJCzOOiCSvnENcjPEgZZcs.py
areixio/databases/TfpHhkSVCToBVFOKMEcnpDxHUgBytiOM.py
areixio/databases/__init__.py
areixio/databases/eAMMdORInEzHrDuDDybFFnfMcbtaXQHZ.py
areixio/databases/faLUTZEUrUVwJPqZZErlTSspbVHegAGs.py
areixio/databases/qkdLGPFaSDSpOeDoBfqmFvyPeErHBinu.py
areixio/databases/sRUUviOqFLzbVHtmOdtNYkMVcqMrFNEl.py
areixio/databases/xEQzOUnCOQXCgTyUIpGHWQDshwWmgqXc.py
areixio/databases/xUOQqpvVYPKwVvRWjrDnPIMDWVZyvYJA.py
areixio/datafeeds/WRMqvhqPepUSBJVAXsOpZqdRsLoCDKOp.py
areixio/datafeeds/ZCNTaaHUYsQExgHYUDVSkEfaNAcEHBAM.py
areixio/datafeeds/__init__.py
areixio/datafeeds/jSlfqrcQANgYPeNVtsDvzPcdGyHUOGjr.py
areixio/exchanges/DCYCxDBCWzEWucwkanyhAvYpVyEGfDvH.py
areixio/exchanges/GIKEKBjpuNjOcAecelmwIRVgZXXQxVsH.py
areixio/exchanges/NppcBuQfaWmMXCGIbmWqejRNVogxSPVg.py
areixio/exchanges/PcsQdydaFmPtLVPbVSfUvzsZRgqIiOik.py
areixio/exchanges/XrcoDwiYIDPTSPxcJIFhYFeuiayEwlsk.py
areixio/exchanges/__init__.py
areixio/exchanges/elraudHoGbqyAXEPMYHxKwqrKSzQFwkC.py
areixio/exchanges/fgsuVttJGQFxXAnNFambRjYMCYHNOxzg.py
areixio/exchanges/gKBPDOLuOEbrQjjCMvMeLavvfgakTlfK.py
areixio/exchanges/gKgJEIelUDLILGftYLBBLIxoRmIMgnDA.py
areixio/exchanges/jsDUTZqKsvnLCxLLyyhlzSWhhqwIYxiR.py
areixio/exchanges/oQoXBBpIalcjmODDBmhLKUiRnCYIxujl.py
areixio/exchanges/qvuqKdwenOlEiOGZFBJApoCfuRlcVoLX.py
areixio/exchanges/rDPjJPBfrShVGQVuApbyGJPocdSrMOzo.py
