Metadata-Version: 2.1
Name: areixio
Version: 0.4.24
Summary: Areix IO Backtesting Framework
Home-page: https://areixio.areix-ai.com/index.html
Author: Areix
Author-email: hellohk@areix-ai.com
Project-URL: Documentation, https://areixio.areix-ai.com/index.html
Keywords: areix,areixio,alpha_gen,alphagen,wealthx,algo,algorithmic,backtest,backtesting,bitcoin,crypto,bokeh,bonds,candle,candlestick,cboe,chart,cme,commodities,crash,currency,drawdown,equity,etf,ethereum,exchange,finance,financial,forecast,forex,fund,futures,fx,gold,historical,indicator,invest,investing,investment,macd,market,money,ohlc,ohlcv,order,price,profit,quant,quantitative,rsi,pnl,stocks,strategy,ticker,trader,trading,tradingview,usd,binance
Classifier: Development Status :: 2 - Pre-Alpha
Classifier: Intended Audience :: Developers
Classifier: Intended Audience :: Financial and Insurance Industry
Classifier: Intended Audience :: Information Technology
Classifier: Topic :: Software Development :: Build Tools
Classifier: Topic :: Office/Business :: Financial :: Investment
Classifier: Programming Language :: Python :: 3.7
Classifier: Programming Language :: Python :: 3.8
Classifier: Programming Language :: Python :: 3.9
Classifier: Programming Language :: Python :: 3.10
Classifier: Programming Language :: Python :: 3.11
Classifier: Operating System :: OS Independent
Classifier: Environment :: Console
Requires-Python: >=3.7.0
